pyscope/__init__.py
pyscope/analysis/__init__.py
pyscope/analysis/calc_zmag.py
pyscope/analysis/detect_sources_photutils.py
pyscope/observatory/__init__.py
pyscope/observatory/_docstring_inheritee.py
pyscope/observatory/_pwi4.py
pyscope/observatory/ascom_camera.py
pyscope/observatory/ascom_cover_calibrator.py
pyscope/observatory/ascom_device.py
pyscope/observatory/ascom_dome.py
pyscope/observatory/ascom_filter_wheel.py
pyscope/observatory/ascom_focuser.py
pyscope/observatory/ascom_observing_conditions.py
pyscope/observatory/ascom_rotator.py
pyscope/observatory/ascom_safety_monitor.py
pyscope/observatory/ascom_switch.py
pyscope/observatory/ascom_telescope.py
pyscope/observatory/autofocus.py
pyscope/observatory/camera.py
pyscope/observatory/collect_calibration_set.py
pyscope/observatory/cover_calibrator.py
pyscope/observatory/device.py
pyscope/observatory/dome.py
pyscope/observatory/filter_wheel.py
pyscope/observatory/focuser.py
pyscope/observatory/html_observing_conditions.py
pyscope/observatory/html_safety_monitor.py
pyscope/observatory/ip_cover_calibrator.py
pyscope/observatory/maxim.py
pyscope/observatory/observatory.py
pyscope/observatory/observatory_exception.py
pyscope/observatory/observing_conditions.py
pyscope/observatory/pwi4_autofocus.py
pyscope/observatory/pwi4_focuser.py
pyscope/observatory/pwi_autofocus.py
pyscope/observatory/rotator.py
pyscope/observatory/safety_monitor.py
pyscope/observatory/simulator_server.py
pyscope/observatory/skyx.py
pyscope/observatory/switch.py
pyscope/observatory/telescope.py
pyscope/reduction/__init__.py
pyscope/reduction/astrometry_net_wcs.py
pyscope/reduction/avg_fits.py
pyscope/reduction/avg_fits_ccdproc.py
pyscope/reduction/calib_images.py
pyscope/reduction/ccd_calib.py
pyscope/reduction/fitslist.py
pyscope/reduction/maxim_pinpoint_wcs.py
pyscope/reduction/pinpoint_wcs.py
pyscope/reduction/process_images.py
pyscope/reduction/reduce_calibration_set.py
pyscope/reduction/twirl_wcs.py
pyscope/telrun/__init__.py
pyscope-0.2.0.dist-info/LICENSE
pyscope-0.2.0.dist-info/METADATA
pyscope-0.2.0.dist-info/WHEEL
pyscope-0.2.0.dist-info/entry_points.txt
pyscope-0.2.0.dist-info/top_level.txt
pyscope-0.2.0.dist-info/RECORD
