Metadata-Version: 2.1
Name: pyscope
Version: 0.2.0
Summary: A python package for controlling small optical telescopes
Author: Walter Golay
Author-email: wgolay@cfa.harvard.edu
License: AGPLv3
Project-URL: Source, https://github.com/macro-consortium/pyscope
Project-URL: Documentation, https://pyscope.readthedocs.io/en/latest/
Keywords: astronomy,astrophysics,telescope,astrophotography,astrometry,photometry,python,automation,ascom,astropy,observatory,observatory automation
Classifier: Development Status :: 4 - Beta
Classifier: Intended Audience :: Developers
Classifier: Intended Audience :: End Users/Desktop
Classifier: Intended Audience :: Other Audience
Classifier: Intended Audience :: Science/Research
Classifier: Intended Audience :: Education
Classifier: License :: OSI Approved :: GNU Affero General Public License v3 or later (AGPLv3+)
Classifier: Natural Language :: English
Classifier: Operating System :: Microsoft :: Windows
Classifier: Operating System :: OS Independent
Classifier: Programming Language :: Python :: 3.12
Classifier: Topic :: Education
Classifier: Topic :: Scientific/Engineering :: Astronomy
Classifier: Topic :: Scientific/Engineering :: Image Processing
Requires-Python: >=3.12
License-File: LICENSE
Requires-Dist: alpyca==2.0.4
Requires-Dist: astroplan==0.10
Requires-Dist: astropy==6.1.1
Requires-Dist: astroquery==0.4.7
Requires-Dist: astroscrappy==1.2.0
Requires-Dist: ccdproc==2.4.2
Requires-Dist: click==8.1.7
Requires-Dist: cmcrameri==1.9
Requires-Dist: markdown==3.6
Requires-Dist: matplotlib==3.9.0
Requires-Dist: numpy==2.0.0
Requires-Dist: oschmod==0.3.12
Requires-Dist: paramiko==3.4.0
Requires-Dist: photutils==1.13.0
Requires-Dist: prettytable==3.10.0
Requires-Dist: scikit-image==0.23.2
Requires-Dist: scipy==1.14.0
Requires-Dist: smplotlib==0.0.9
Requires-Dist: timezonefinder==6.5.0
Requires-Dist: tksheet==7.2.4
Requires-Dist: tqdm==4.66.4
Requires-Dist: pywin32==306; platform_system == "Windows"
Provides-Extra: dev
Requires-Dist: black==24.3.0; extra == "dev"
Requires-Dist: build==1.2.1; extra == "dev"
Requires-Dist: docutils==0.20.1; extra == "dev"
Requires-Dist: esbonio==0.16.4; extra == "dev"
Requires-Dist: isort==5.13.2; extra == "dev"
Requires-Dist: pre-commit==3.7.0; extra == "dev"
Requires-Dist: pytest==8.1.1; extra == "dev"
Requires-Dist: pytest-cov==5.0.0; extra == "dev"
Requires-Dist: pytest-order==1.2.1; extra == "dev"
Requires-Dist: rstcheck==6.2.1; extra == "dev"
Requires-Dist: sphinx==7.2.6; extra == "dev"
Requires-Dist: sphinx-astropy[confv2]==1.9.1; extra == "dev"
Requires-Dist: sphinx-favicon==1.0.1; extra == "dev"
Requires-Dist: sphinxcontrib-programoutput==0.17; extra == "dev"
Requires-Dist: twine==5.0.0; extra == "dev"
Provides-Extra: docs
Requires-Dist: sphinx==7.2.6; extra == "docs"
Requires-Dist: sphinx-astropy[confv2]==1.9.1; extra == "docs"
Requires-Dist: sphinx-favicon==1.0.1; extra == "docs"
Requires-Dist: sphinxcontrib-programoutput==0.17; extra == "docs"
Provides-Extra: tests
Requires-Dist: pytest==8.1.1; extra == "tests"
Requires-Dist: pytest-cov==5.0.0; extra == "tests"
Requires-Dist: pytest-doctestplus==1.2.1; extra == "tests"
